{
  "organization": {
    "name": "人社青年",
    "tagline": "用學生的眼光看人社，用人社的視角看社會",
    "mission": "我們是一群對人文社會充滿熱忱的青年，透過議題整理、知識轉譯與刊物書寫，讓更多人能一步步靠近公共參與。",
    "avatarUrl": "",
    "instagram": {
      "handle": "@youth.hss",
      "url": "https://www.instagram.com/youth.hss/",
      "followers": "1,486",
      "posts": "93",
      "following": "58"
    },
    "appearance": {
      "brandMarkText": "RY"
    },
    "about": [
      "人社青年由一群關心公共參與與人文社會議題的高中生、大學生組成，希望把抽象的概念變成更多人都能理解的內容。",
      "我們透過 Instagram、網站刊物與議題整理，讓社會建構、特權、自由、轉型正義等討論更接近日常，也更容易展開對話。",
      "我們相信公共參與不只是少數人的工作，而是一種可以被學習、被練習，也能被更多青年一起接住的行動。 "
    ],
    "themes": [
      "公共參與",
      "社會議題",
      "人文社會",
      "知識轉譯",
      "青年觀點"
    ],
    "highlights": [
      "把複雜的人文社會議題轉譯成更容易閱讀的內容",
      "從青年視角出發，整理公共討論中的重要概念與脈絡",
      "用刊物與社群內容累積更多可持續的參與入口"
    ]
  },
  "donation": {
    "title": "支持人社青年持續做內容",
    "summary": "你的支持會幫助我們維持議題整理、網站更新、刊物撰寫與青年公共參與行動，讓更多人能透過內容接近社會議題。",
    "showTarget": true,
    "target": 500000,
    "raised": 186400,
    "accounts": [
      "支持網站維運與內容整理",
      "支持刊物編輯、排版與發布",
      "支持青年公共參與與知識轉譯工作"
    ],
    "bankTransfer": {
      "bankName": "玉山銀行",
      "accountName": "人社青年",
      "accountNumber": "808-1234-5678-9012",
      "note": "匯款後可私訊 Instagram，方便我們確認與致謝。"
    }
  },
  "publications": [
    {
      "id": 1,
      "title": "刊物 Vol.01｜從社會建構理解我們如何看世界",
      "description": "從社會建構論出發，重新思考哪些觀念看似自然，其實是被社會形塑而成。",
      "tag": "社會建構",
      "content": "當我們說某些價值、身分或規範『本來就是這樣』時，往往忽略了它們其實是在特定歷史與社會條件下逐步形成的。社會建構論提醒我們，看似自然的事物，常常帶有時代、制度與權力的痕跡。\n\n理解社會建構，不是為了否認經驗本身，而是讓我們多一個角度去看待規範如何形成、誰擁有命名的權力，以及哪些聲音在過程中被排除。\n\n當我們開始意識到『理所當然』也可能是被建構的，我們就更有機會重新打開討論、鬆動偏見，並讓更多人能進入公共對話。"
    },
    {
      "id": 2,
      "title": "刊物 Vol.02｜特權不是指責，而是理解不平等的起點",
      "description": "從日常經驗出發，重新理解特權如何存在，以及它為什麼值得被討論。",
      "tag": "特權",
      "content": "談到特權時，很多人第一時間會感到防衛，彷彿這個詞是在否定個人的努力。但特權真正要指出的，不是誰不夠努力，而是不同人起跑的位置、本來就不完全相同。\n\n性別、家庭資源、教育機會、居住環境與社會期待，都可能在不知不覺中影響一個人可見的選擇。看見特權，不是為了羞愧，而是為了更誠實地理解不平等如何運作。\n\n只有當我們願意辨認那些原本被視為『正常』的優勢，公共討論才可能走向更具體、更有回應力的改變。"
    }
  ]
}
